pergola/__init__.py
pergola/_version.py
pergola/intervals.py
pergola/isatab_parser.py
pergola/jaaba_parsers.py
pergola/mapping.py
pergola/parsers.py
pergola/tracks.py
scripts/__init__.py
scripts/jaaba_to_pergola.py
scripts/pergola_isatab.py
scripts/pergola_rules.py
pergola-0.2.0.dist-info/LICENSE
pergola-0.2.0.dist-info/METADATA
pergola-0.2.0.dist-info/WHEEL
pergola-0.2.0.dist-info/entry_points.txt
pergola-0.2.0.dist-info/top_level.txt
pergola-0.2.0.dist-info/RECORD
